jupyterlab_stata_highlight2/__init__.py
jupyterlab_stata_highlight2/_version.py
jupyterlab_stata_highlight2/labextension/package.json
jupyterlab_stata_highlight2/labextension/static/747.715fbd3bd96785e56a91.js
jupyterlab_stata_highlight2/labextension/static/897.ae47d06ba3d441872533.js
jupyterlab_stata_highlight2/labextension/static/remoteEntry.28113fc47152cf8d974e.js
jupyterlab_stata_highlight2/labextension/static/style.js
jupyterlab_stata_highlight2/labextension/static/third-party-licenses.json
jupyterlab_stata_highlight2-0.1.2.data/data/share/jupyter/labextensions/jupyterlab_stata_highlight2/install.json
jupyterlab_stata_highlight2-0.1.2.data/data/share/jupyter/labextensions/jupyterlab_stata_highlight2/package.json
jupyterlab_stata_highlight2-0.1.2.data/data/share/jupyter/labextensions/jupyterlab_stata_highlight2/static/747.715fbd3bd96785e56a91.js
jupyterlab_stata_highlight2-0.1.2.data/data/share/jupyter/labextensions/jupyterlab_stata_highlight2/static/897.ae47d06ba3d441872533.js
jupyterlab_stata_highlight2-0.1.2.data/data/share/jupyter/labextensions/jupyterlab_stata_highlight2/static/remoteEntry.28113fc47152cf8d974e.js
jupyterlab_stata_highlight2-0.1.2.data/data/share/jupyter/labextensions/jupyterlab_stata_highlight2/static/style.js
jupyterlab_stata_highlight2-0.1.2.data/data/share/jupyter/labextensions/jupyterlab_stata_highlight2/static/third-party-licenses.json
jupyterlab_stata_highlight2-0.1.2.dist-info/METADATA
jupyterlab_stata_highlight2-0.1.2.dist-info/WHEEL
jupyterlab_stata_highlight2-0.1.2.dist-info/licenses/LICENSE
jupyterlab_stata_highlight2-0.1.2.dist-info/RECORD
