Metadata-Version: 2.1
Name: jupyterlab_stata_highlight2
Version: 0.1.2
Summary: JupyterLab extension for Stata syntax highlighting similar to the Stata IDE's.
Project-URL: Homepage, https://github.com/hugetim/jupyterlab_stata_highlight2
Author-email: Tim Huegerich <hugetim@gmail.com>
License: 
License-File: LICENSE
Keywords: Jupyter,JupyterLab,JupyterLab3
Classifier: Framework :: Jupyter
Classifier: Framework :: Jupyter :: JupyterLab
Classifier: Framework :: Jupyter :: JupyterLab :: 3
Classifier: Framework :: Jupyter :: JupyterLab :: Extensions
Classifier: Framework :: Jupyter :: JupyterLab :: Extensions :: Prebuilt
Classifier: License :: OSI Approved :: MIT License
Classifier: Programming Language :: Python
Classifier: Programming Language :: Python :: 3
Classifier: Programming Language :: Python :: 3.7
Classifier: Programming Language :: Python :: 3.8
Classifier: Programming Language :: Python :: 3.9
Classifier: Programming Language :: Python :: 3.10
Requires-Python: >=3.7
